smcp/__init__.py
smcp/allowlist.py
smcp/app_wrapper.py
smcp/confirm.py
smcp/cpu.py
smcp/decorators.py
smcp/enforce.py
smcp/filters.py
smcp/license.py
smcp/logchain.py
smcp/tls.py
smcp/cli/__init__.py
smcp/cli/approve.py
smcp/cli/gen_key.py
smcp/cli/mkcert.py
smcp/cli/revoke.py
smcp_biz-0.1.0.dist-info/METADATA
smcp_biz-0.1.0.dist-info/WHEEL
smcp_biz-0.1.0.dist-info/entry_points.txt
smcp_biz-0.1.0.dist-info/top_level.txt
smcp_biz-0.1.0.dist-info/RECORD
