Metadata-Version: 2.4
Name: smcp-biz
Version: 0.1.0
Summary: SMCP Business Edition - Secure Model Context Protocol with advanced licensing
Author-email: BizTeam AI <support@bizteamai.com>
License: Commercial
Project-URL: Homepage, https://github.com/bizteamai
Project-URL: Documentation, https://github.com/bizteamai/smcp-biz
Project-URL: Repository, https://github.com/bizteamai/smcp-biz
Project-URL: Bug Tracker, https://github.com/bizteamai/smcp-biz/issues
Classifier: Development Status :: 4 - Beta
Classifier: Intended Audience :: Developers
Classifier: License :: Other/Proprietary License
Classifier: Programming Language :: Python :: 3
Classifier: Programming Language :: Python :: 3.10
Classifier: Programming Language :: Python :: 3.11
Classifier: Programming Language :: Python :: 3.12
Requires-Python: >=3.10
Requires-Dist: mcp
Requires-Dist: fastmcp
Requires-Dist: cryptography
Requires-Dist: pyyaml
Requires-Dist: psutil>=5.8.0
Requires-Dist: requests>=2.25.0
Provides-Extra: support
Requires-Dist: psutil>=5.8.0; extra == "support"
Requires-Dist: requests>=2.25.0; extra == "support"
